PIL/__init__.py
albums/__init__.py
albums/admin.py
albums/api.py
albums/apps.py
albums/filters.py
albums/forms.py
albums/managers.py
albums/mixins.py
albums/models.py
albums/schema.py
albums/tables.py
albums/tests.py
albums/urls.py
albums/views.py
albums/migrations/0001_initial.py
albums/migrations/0002_initial.py
albums/migrations/__init__.py
albums/templates/album_detail.html
albums/templates/album_detail_grid.html
albums/templates/album_detail_table.html
albums/templates/album_form.html
albums/templates/album_list.html
albums/templates/includes/album_filters.html
albums/templates/includes/album_list_table.html
albums/templates/includes/album_sidebar.html
albums/templates/includes/album_toolbar.html
assets/css/bma.scss
assets/css/package.json
audios/__init__.py
audios/apps.py
audios/models.py
audios/migrations/0001_initial.py
audios/migrations/__init__.py
bma/.env.dist
bma/__init__.py
bma/api.py
bma/asgi.py
bma/environment_settings.py
bma/environment_settings.py.ci
bma/environment_settings.py.dist
bma/oauth2_urls.py
bma/settings.py
bma/urls.py
bma/wsgi.py
bma/formats/__init__.py
bma/formats/en/__init__.py
bma/formats/en/formats.py
bornhack_allauth_provider/__init__.py
bornhack_allauth_provider/adapters.py
bornhack_allauth_provider/apps.py
bornhack_allauth_provider/client.py
bornhack_allauth_provider/provider.py
bornhack_allauth_provider/urls.py
bornhack_allauth_provider/views.py
documents/__init__.py
documents/apps.py
documents/models.py
documents/migrations/0001_initial.py
documents/migrations/__init__.py
files/__init__.py
files/admin.py
files/api.py
files/apps.py
files/filters.py
files/forms.py
files/managers.py
files/mixins.py
files/models.py
files/schema.py
files/tables.py
files/tests.py
files/urls.py
files/validators.py
files/views.py
files/migrations/0001_initial.py
files/migrations/0002_initial.py
files/migrations/0003_initial.py
files/migrations/0004_initial.py
files/migrations/__init__.py
files/templates/file_albums.html
files/templates/file_detail.html
bma-0.2.0a2.dist-info/LICENSE
bma-0.2.0a2.dist-info/METADATA
bma-0.2.0a2.dist-info/WHEEL
bma-0.2.0a2.dist-info/entry_points.txt
bma-0.2.0a2.dist-info/top_level.txt
bma-0.2.0a2.dist-info/RECORD
