Metadata-Version: 2.1
Name: bma
Version: 0.2.0a2
Summary: BornHack Media Archive Django project
Author: Thomas Steen Rasmussen
Author-email: thomas@gibfest.dk
Project-URL: homepage, https://github.com/bornhack/bma
Classifier: Programming Language :: Python :: 3
Classifier: Operating System :: OS Independent
Requires-Python: >=3.11
License-File: LICENSE
Requires-Dist: demoji==1.1.0
Requires-Dist: Django==5.1.4
Requires-Dist: django-allauth[socialaccount]==65.3.0
Requires-Dist: django-bootstrap5==24.3
Requires-Dist: django-cors-headers==4.6.0
Requires-Dist: django-decorator-include==3.2
Requires-Dist: django-filter==24.3
Requires-Dist: django-guardian==2.4.0
Requires-Dist: django-htmx==1.21.0
Requires-Dist: django-ninja==1.3.0
Requires-Dist: django-oauth-toolkit==3.0.1
Requires-Dist: django-polymorphic==3.1.0
Requires-Dist: django-stubs-ext==5.1.1
Requires-Dist: django-tables2==2.7.0
Requires-Dist: django-taggit==6.1.0
Requires-Dist: environs[django]==11.2.1
Requires-Dist: fontawesomefree==6.6.0
Requires-Dist: orjson==3.10.12
Requires-Dist: psycopg2-binary==2.9.10
Provides-Extra: dev
Requires-Dist: pre-commit==4.0.1; extra == "dev"
Requires-Dist: setuptools_scm==8.1.0; extra == "dev"
Provides-Extra: test
Requires-Dist: beautifulsoup4==4.12.3; extra == "test"
Requires-Dist: coverage==7.6.9; extra == "test"
Requires-Dist: django-debug-toolbar==4.4.6; extra == "test"
Requires-Dist: factory-boy==3.3.1; extra == "test"
Requires-Dist: pytest-django==4.9.0; extra == "test"
Requires-Dist: pytest-cov==6.0.0; extra == "test"
Requires-Dist: pytest-randomly==3.16.0; extra == "test"
Requires-Dist: tox==4.23.2; extra == "test"
